{
  "auth": {
    "todoappf71829bff71829bf": {
      "customAuth": false,
      "dependsOn": [],
      "frontendAuthConfig": {
        "mfaConfiguration": "OFF",
        "mfaTypes": [
          "SMS"
        ],
        "passwordProtectionSettings": {
          "passwordPolicyCharacters": [],
          "passwordPolicyMinLength": 8
        },
        "signupAttributes": [
          "EMAIL"
        ],
        "socialProviders": [
          "GOOGLE"
        ],
        "usernameAttributes": [
          "EMAIL"
        ],
        "verificationMechanisms": [
          "PHONE_NUMBER"
        ]
      },
      "providerPlugin": "awscloudformation",
      "service": "Cognito"
    }
  }
}